{"cameraMode":{"drawMode":0,"name":"Shaded","section":"Shading Mode"},"sceneLighting":false,"audioPlay":false,"sceneViewState":{"m_AlwaysRefresh":false,"showFog":true,"showSkybox":false,"showFlares":true,"showImageEffects":true,"showParticleSystems":true,"showVisualEffectGraphs":true,"m_FxEnabled":true},"in2DMode":false,"pivot":{"x":-4.9580254554748539,"y":-0.24448227882385255,"z":4.12764835357666},"rotation":{"x":0.2995609939098358,"y":-0.6360864639282227,"z":0.2944783568382263,"w":0.6473095417022705},"size":0.8660253882408142,"orthographic":false}